flask_humanize/__init__.py
flask_humanize/compat.py
Humanize_Flask-0.2.0.dist-info/DESCRIPTION.rst
Humanize_Flask-0.2.0.dist-info/METADATA
Humanize_Flask-0.2.0.dist-info/metadata.json
Humanize_Flask-0.2.0.dist-info/RECORD
Humanize_Flask-0.2.0.dist-info/top_level.txt
Humanize_Flask-0.2.0.dist-info/WHEEL
