Metadata-Version: 2.0
Name: Humanize-Flask
Version: 0.2.0
Summary: Common humanization utilities for Flask applications.
Home-page: https://github.com/vitalk/flask-humanize
Author: Vital Kudzelka
Author-email: vital.kudzelka@gmail.com
License: MIT
Download-URL: https://github.com/vitalk/flask-humanize/tarball/0.2.0
Keywords: flask humanize datetime
Platform: any
Classifier: Development Status :: 4 - Beta
Classifier: Environment :: Plugins
Classifier: Environment :: Web Environment
Classifier: Intended Audience :: Developers
Classifier: License :: OSI Approved :: MIT License
Classifier: Operating System :: OS Independent
Classifier: Programming Language :: Python
Classifier: Programming Language :: Python :: 2
Classifier: Programming Language :: Python :: 2.6
Classifier: Programming Language :: Python :: 2.7
Classifier: Programming Language :: Python :: 3
Classifier: Programming Language :: Python :: 3.3
Classifier: Programming Language :: Python :: 3.4
Classifier: Programming Language :: Python :: Implementation :: CPython
Classifier: Programming Language :: Python :: Implementation :: PyPy
Classifier: Framework :: Flask
Classifier: Topic :: Internet :: WWW/HTTP :: Dynamic Content
Classifier: Topic :: Software Development :: Libraries :: Python Modules
Requires-Dist: Flask
Requires-Dist: humanize (>=0.5.1)
